thousandeyes_sdk/labels/__init__.py
thousandeyes_sdk/labels/py.typed
thousandeyes_sdk/labels/api/__init__.py
thousandeyes_sdk/labels/api/agent_api.py
thousandeyes_sdk/labels/api/all_labels_api.py
thousandeyes_sdk/labels/api/dashboard_api.py
thousandeyes_sdk/labels/api/endpoint_test_api.py
thousandeyes_sdk/labels/api/test_api.py
thousandeyes_sdk/labels/models/__init__.py
thousandeyes_sdk/labels/models/error.py
thousandeyes_sdk/labels/models/label.py
thousandeyes_sdk/labels/models/label_detail.py
thousandeyes_sdk/labels/models/label_request.py
thousandeyes_sdk/labels/models/label_type.py
thousandeyes_sdk/labels/models/labels.py
thousandeyes_sdk/labels/models/link.py
thousandeyes_sdk/labels/models/self_links.py
thousandeyes_sdk/labels/models/unauthorized_error.py
thousandeyes_sdk/labels/models/validation_error.py
thousandeyes_sdk/labels/models/validation_error_item.py
thousandeyes_sdk_labels-1.1.0.dist-info/LICENSE
thousandeyes_sdk_labels-1.1.0.dist-info/METADATA
thousandeyes_sdk_labels-1.1.0.dist-info/NOTICE
thousandeyes_sdk_labels-1.1.0.dist-info/WHEEL
thousandeyes_sdk_labels-1.1.0.dist-info/top_level.txt
thousandeyes_sdk_labels-1.1.0.dist-info/RECORD
